{
    "enabled": true,
    "neededInstalledMods": [],
    "neededUninstalledMods": [],
    "spawns": [
        {
            "id": "croconaw-1",
            "pokemon": "croconaw",
            "presets": ["natural"],
            "type": "pokemon",
            "spawnablePositionType": "grounded",
            "bucket": "rare",
            "level": "18-36",
            "weight": 2.0,
            "condition": {
                "minSkyLight": 8,
                "maxSkyLight": 15,
                "biomes": ["#cobblemon:is_river", "#cobblemon:is_swamp"]
            }
        }
    ]
}
